python_rave/__init__.py
python_rave/rave.py
python_rave/rave_account.py
python_rave/rave_base.py
python_rave/rave_card.py
python_rave/rave_exceptions.py
python_rave/rave_ghmobile.py
python_rave/rave_misc.py
python_rave/rave_mpesa.py
python_rave/rave_payment.py
python_rave/rave_preauth.py
python_rave/rave_transfer.py
python_rave/rave_ussd.py
python_rave-1.0.10a0.dist-info/METADATA
python_rave-1.0.10a0.dist-info/RECORD
python_rave-1.0.10a0.dist-info/WHEEL
python_rave-1.0.10a0.dist-info/top_level.txt
