Metadata-Version: 2.1
Name: python-rave
Version: 1.0.10a0
Summary: A python wrapper for Flutterwave's Rave
Home-page: https://github.com/TofunmiKupoluyi/python_rave
Author: Tofunmi Kupoluyi
Author-email: tofunmi@flutterwavego.com
License: UNKNOWN
Platform: UNKNOWN
Classifier: Programming Language :: Python :: 3
Classifier: License :: OSI Approved :: MIT License
Classifier: Operating System :: OS Independent
Requires-Dist: PyCrypto
Requires-Dist: requests
